{
  "version": "36.0.18",
  "files": {
    "c84a7003635a1edc75fcd8f987311e3e401f01ff4636b5011bb8beeb6d126a8c": {
      "source": {
        "path": "CredentialsPriorityStack.template.json",
        "packaging": "file"
      },
      "destinations": {
        "current_account-current_region": {
          "bucketName": "cdk-hnb659fds-assets-${AWS::AccountId}-${AWS::Region}",
          "objectKey": "c84a7003635a1edc75fcd8f987311e3e401f01ff4636b5011bb8beeb6d126a8c.json",
          "assumeRoleArn": "arn:${AWS::Partition}:iam::${AWS::AccountId}:role/cdk-hnb659fds-file-publishing-role-${AWS::AccountId}-${AWS::Region}"
        }
      }
    }
  },
  "dockerImages": {}
}